setup.py
hello/__init__.py
hello/hello.py
hello_baby0.egg-info/PKG-INFO
hello_baby0.egg-info/SOURCES.txt
hello_baby0.egg-info/dependency_links.txt
hello_baby0.egg-info/top_level.txt